coubeh/__init__.py
feur/__init__.py
quoi/__init__.py
quoi-2.0.dist-info/LICENSE
quoi-2.0.dist-info/METADATA
quoi-2.0.dist-info/WHEEL
quoi-2.0.dist-info/top_level.txt
quoi-2.0.dist-info/RECORD
