Metadata-Version: 2.1
Name: quoi
Version: 2.0
Summary: bruh
Home-page: https://github.com
Author: Timothé Boulet
Author-email: timothe.boulet0@gmail.com
License: MIT
License-File: LICENSE
